yaml_lex/__init__.py
yaml_lex/__main__.py
yaml_lex/format.py
yaml_lex/watch.py
yaml_lex-0.2.2.dist-info/METADATA
yaml_lex-0.2.2.dist-info/WHEEL
yaml_lex-0.2.2.dist-info/entry_points.txt
yaml_lex-0.2.2.dist-info/top_level.txt
yaml_lex-0.2.2.dist-info/RECORD
