Metadata-Version: 2.4
Name: yaml-lex
Version: 0.2.2
Summary: A corpus-statutes YAML formatter with smart wrapping rules
Requires-Python: >=3.13
Requires-Dist: click>=8.2.1
Requires-Dist: PyYAML>=6.0.3
Requires-Dist: rich>=14.1
Requires-Dist: watchdog>=6.0.0
Provides-Extra: dev
Requires-Dist: jupyter>=1.1.1; extra == "dev"
Requires-Dist: notebook>=7.4.3; extra == "dev"
Requires-Dist: mkdocs>=1.6.1; extra == "dev"
Requires-Dist: mkdocs-material>=9.6.20; extra == "dev"
Requires-Dist: mkdocstrings[python]>=0.30.1; extra == "dev"
Requires-Dist: pytest>=8.4; extra == "dev"
Requires-Dist: pytest-cov>=5.0; extra == "dev"
